{
    "date_from": "03.2020",
    "title": "Website paulscafebar.com",
    "subtitle": "1 day, remote",
    "classes": "print_not is_collapsed",
    "blocks": [
        {
            "image": "icon_sass",
            "caption": "SASS",
            "description": "Creation of a static website for a café. Responsibilities:",
            "points": ["Website development", "Website deployment"]
        }
    ],
    "techs": [
        {
            "image": "icon_css3",
            "caption": "CSS3"
        },
        {
            "image": "icon_javascript_bg",
            "caption": "JavaScript"
        },
        {
            "image": "icon_gsap",
            "caption": "GSAP"
        },
        {
            "image": "icon_webpack",
            "caption": "Webpack"
        },
        {
            "image": "icon_git",
            "caption": "Git"
        }
    ]
}
